file_template/__init__.py
file_template/cli.py
file_template-1.1.0.dist-info/entry_points.txt
file_template-1.1.0.dist-info/LICENSE.txt
file_template-1.1.0.dist-info/WHEEL
file_template-1.1.0.dist-info/METADATA
file_template-1.1.0.dist-info/RECORD
