Metadata-Version: 2.1
Name: file-template
Version: 1.1.0
Summary: 
Home-page: https://github.com/LivinParadoX/file-template/
License: AGPL-3.0-or-later
Author: Alexandre Janvrin
Author-email: alexandre.janvrin@reseau.eseo.fr
Requires-Python: >=3.9,<4.0
Classifier: License :: OSI Approved :: GNU Affero General Public License v3 or later (AGPLv3+)
Classifier: Natural Language :: English
Classifier: Operating System :: OS Independent
Classifier: Programming Language :: Python
Classifier: Programming Language :: Python :: 3
Classifier: Programming Language :: Python :: 3.9
Requires-Dist: click (>=7.1.2,<8.0.0)
Project-URL: Repository, https://pypi.org/project/file-template/
